logsett/__init__.py
logsett/logger_settings.py
logsett-2023.0.0.dist-info/LICENSE
logsett-2023.0.0.dist-info/METADATA
logsett-2023.0.0.dist-info/WHEEL
logsett-2023.0.0.dist-info/top_level.txt
logsett-2023.0.0.dist-info/RECORD
