Metadata-Version: 2.1
Name: logsett
Version: 2023.0.0
Summary: logger settings
Author-email: moronstone <moronstone@moron.com>
License: MIT License
Keywords: logger
Classifier: Programming Language :: Python :: 3
Classifier: License :: OSI Approved :: MIT License
Classifier: Operating System :: OS Independent
Requires-Python: >=3.9
License-File: LICENSE
Requires-Dist: colorama ==0.4.6
Requires-Dist: loguru ==0.7.2
Requires-Dist: win32-setctime ==1.1.0
